django_extensions_too/__init__.py
django_extensions_too/models.py
django_extensions_too/management/__init__.py
django_extensions_too/management/color.py
django_extensions_too/management/commands/__init__.py
django_extensions_too/management/commands/add_proxy_permissions.py
django_extensions_too/management/commands/delete_unreferenced_files.py
django_extensions_too/management/commands/get_all_permissions.py
django_extensions_too/management/commands/manifest_storage_check.py
django_extensions_too/management/commands/missing_files.py
django_extensions_too/management/commands/remove_app.py
django_extensions_too-0.1.7.dist-info/AUTHORS.md
django_extensions_too-0.1.7.dist-info/LICENSE
django_extensions_too-0.1.7.dist-info/METADATA
django_extensions_too-0.1.7.dist-info/WHEEL
django_extensions_too-0.1.7.dist-info/top_level.txt
django_extensions_too-0.1.7.dist-info/RECORD
